bgnlp/__init__.py
bgnlp/models/__init__.py
bgnlp/models/bert.py
bgnlp/models/seq2seq.py
bgnlp/serialized/__init__.py
bgnlp/serialized/models/__init__.py
bgnlp/serialized/vocabs/cb-vocab.pt
bgnlp/tools/__init__.py
bgnlp/tools/configs.py
bgnlp/tools/mappings.py
bgnlp/tools/mixins.py
bgnlp/tools/taggers.py
bgnlp/tools/tokenizers.py
bgnlp-0.5.3.dist-info/LICENSE
bgnlp-0.5.3.dist-info/METADATA
bgnlp-0.5.3.dist-info/WHEEL
bgnlp-0.5.3.dist-info/top_level.txt
bgnlp-0.5.3.dist-info/RECORD
